spreedly/__init__.py
spreedly/client.py
spreedly/exception.py
hts_spreedly-0.1.1.dist-info/METADATA
hts_spreedly-0.1.1.dist-info/WHEEL
hts_spreedly-0.1.1.dist-info/RECORD
