Metadata-Version: 2.1
Name: hts-spreedly
Version: 0.1.1
Summary: Spreedly API client for Python
License: Apache-2.0
Author: Leonard Law
Author-email: llaw@hopper.com
Requires-Python: >=3.10,<4.0
Classifier: License :: OSI Approved :: Apache Software License
Classifier: Programming Language :: Python :: 3
Classifier: Programming Language :: Python :: 3.10
Classifier: Programming Language :: Python :: 3.11
Classifier: Programming Language :: Python :: 3.12
Requires-Dist: cryptography (>=43.0.1,<44.0.0)
Requires-Dist: httpx (>=0.27.2,<0.28.0)
